MANIFEST.in
README.md
setup.py
cartridge_payments.egg-info/PKG-INFO
cartridge_payments.egg-info/SOURCES.txt
cartridge_payments.egg-info/dependency_links.txt
cartridge_payments.egg-info/entry_points.txt
cartridge_payments.egg-info/not-zip-safe
cartridge_payments.egg-info/top_level.txt
payments/__init__.py
payments/multipayments/__init__.py
payments/multipayments/const.py
payments/multipayments/context_processors.py
payments/multipayments/forms/__init__.py
payments/multipayments/forms/base.py
payments/multipayments/forms/google.py
payments/multipayments/forms/paypal.py
payments/multipayments/templates/shop/payment.html
payments/multipayments/templates/shop/includes/payment_fields.html
payments/multipayments/templatetags/__init__.py
payments/multipayments/templatetags/multipayment_forms.py