Metadata-Version: 1.0
Name: cartridge-payments
Version: 0.97.0
Summary: Cartridge multiple payment options module.
Home-page: https://github.com/explodes/cartridge-payments
Author: Evan Leis
Author-email: engineergod@yahoo.com
License: Apache Software License
Platform: UNKNOWN
Classifier: Programming Language :: Python
Classifier: Programming Language :: Python :: 2.6
Classifier: Development Status :: 4 - Beta
Classifier: Environment :: Other Environment
Classifier: Intended Audience :: Developers
Classifier: License :: OSI Approved :: Apache Software License
Classifier: Operating System :: OS Independent
Classifier: Topic :: Software Development :: Libraries :: Python Modules
Classifier: Framework :: Django
